{
    "version": "0.2",
    "language": "en",
    "words": [
        "addopts",
        "allclose",
        "celerybeat",
        "Chaieb",
        "Charyton",
        "colorama",
        "conftest",
        "Connor",
        "cumsum",
        "cython",
        "Dataclasses",
        "dmypy",
        "docstrings",
        "fftfreq",
        "flac",
        "Foresman",
        "freqs",
        "Gauthier",
        "Healthline",
        "htmlcov",
        "ifft",
        "iniconfig",
        "ipynb",
        "ipython",
        "isort",
        "Jirakittayakorn",
        "Kraus",
        "levelname",
        "mccabe",
        "mkdocs",
        "mypy",
        "ndarray",
        "neurochemical",
        "nosetests",
        "nperseg",
        "NREM",
        "numpy",
        "Oster",
        "pathspec",
        "pipenv",
        "Pipfile",
        "platformdirs",
        "pluggy",
        "Poirier",
        "polyfit",
        "Porubanová",
        "Prinsloo",
        "pybuilder",
        "pycache",
        "pyenv",
        "pyflow",
        "pylint",
        "pypa",
        "pypackages",
        "pypirc",
        "pyproject",
        "pytest",
        "pytype",
        "pyyaml",
        "randn",
        "Reber",
        "ropeproject",
        "scipy",
        "Scouarnec",
        "scrapy",
        "sdist",
        "soundfile",
        "Spyder",
        "spyderproject",
        "spyproject",
        "Stumbrys",
        "testpaths",
        "tobytes",
        "tomlkit",
        "topdir",
        "VENV",
        "Wahbeh",
        "webassets",
        "Wilpert",
        "Wongsawat"
    ],
    "ignoreWords": [],
    "ignorePaths": []
}
